{
    "generated_at_utc":  "2026-03-14T23:25:23.6486819Z",
    "mirror_root":  "C:\\Mason2_MIRROR",
    "changed_count":  6,
    "added_count":  0,
    "modified_count":  6,
    "removed_count":  0,
    "top_changed_paths":  [
                              "docs/knowledge_pack/index.json",
                              "docs/knowledge_pack/stats.json",
                              "docs/mirror_delta.json",
                              "docs/mirror_manifest.json",
                              "state/knowledge/budget_state.json",
                              "state/knowledge/internal_scheduler_registry.json"
                          ],
    "head_before":  "09fd2b06517af114dd2c3151a5228903bb79641a",
    "head_after":  "c601633230662b67288efe3b95948d652392de20"
}
